src/__init__.py
src/typed_dataclass.py
tests/__init__.py
tests/test_typed_dataclass.py
typed_dataclass/__init__.py
typed_dataclass/typed_dataclass.py
typed_dataclass-0.1.0.dist-info/LICENSE
typed_dataclass-0.1.0.dist-info/METADATA
typed_dataclass-0.1.0.dist-info/WHEEL
typed_dataclass-0.1.0.dist-info/top_level.txt
typed_dataclass-0.1.0.dist-info/RECORD
