Metadata-Version: 2.1
Name: typed-dataclass
Version: 0.1.0
Summary: A decorator for Python dataclasses to enable runtime type checking.
Home-page: https://github.com/ManuelZierl/typed-dataclass
Author: Manuel Zierl
Author-email: manuel.zierl@web.de
Classifier: Programming Language :: Python :: 3
Classifier: License :: OSI Approved :: MIT License
Classifier: Operating System :: OS Independent
Requires-Python: >=3.7
License-File: LICENSE
Requires-Dist: typeguard
